Metadata-Version: 2.2
Name: datasette-enrichments-slow
Version: 0.3
Summary: An enrichment on a slow loop to help debug progress bars
Author: Simon Willison
License: Apache-2.0
Project-URL: Homepage, https://github.com/datasette/datasette-enrichments-slow
Project-URL: Changelog, https://github.com/datasette/datasette-enrichments-slow/releases
Project-URL: Issues, https://github.com/datasette/datasette-enrichments-slow/issues
Project-URL: CI, https://github.com/datasette/datasette-enrichments-slow/actions
Classifier: Framework :: Datasette
Classifier: License :: OSI Approved :: Apache Software License
Requires-Python: >=3.9
License-File: LICENSE
Requires-Dist: datasette
Requires-Dist: datasette-enrichments>=0.5
Provides-Extra: test
Requires-Dist: pytest; extra == "test"
Requires-Dist: pytest-asyncio; extra == "test"
